README.md
setup.cfg
setup.py
read_hnd/__init__.py
read_hnd/__main__.py
read_hnd/command_line.py
read_hnd/read_hnd.py
read_hnd.egg-info/PKG-INFO
read_hnd.egg-info/SOURCES.txt
read_hnd.egg-info/dependency_links.txt
read_hnd.egg-info/entry_points.txt
read_hnd.egg-info/not-zip-safe
read_hnd.egg-info/requires.txt
read_hnd.egg-info/top_level.txt
read_hnd/test_data/Proj_00000.hnd