Metadata-Version: 1.0
Name: read-hnd
Version: 0.2.3
Summary: Package to read .HND format images
Home-page: UNKNOWN
Author: Ben George
Author-email: ben.geroge@oncology.ox.ac.uk
License: UNKNOWN
Platform: UNKNOWN
